coreml_torch_utils/__init__.py
coreml_torch_utils/utils/__init__.py
coreml_torch_utils/utils/export_utils.py
coreml_pytorch_utils-0.1.2.dist-info/WHEEL
coreml_pytorch_utils-0.1.2.dist-info/METADATA
coreml_pytorch_utils-0.1.2.dist-info/LICENSE
coreml_pytorch_utils-0.1.2.dist-info/RECORD
